yorkshire4/__init__.py
yorkshire4/terminal.py
yorkshire4-0.0.0.dist-info/DESCRIPTION.rst
yorkshire4-0.0.0.dist-info/METADATA
yorkshire4-0.0.0.dist-info/RECORD
yorkshire4-0.0.0.dist-info/WHEEL
yorkshire4-0.0.0.dist-info/metadata.json
yorkshire4-0.0.0.dist-info/top_level.txt
